ctao_simpipe-0.2.0.dist-info/licenses/LICENSE
simpipe/__init__.py
simpipe/_version.py
simpipe/version.py
simpipe/tests/__init__.py
simpipe/tests/test_mongo_connection.py
ctao_simpipe-0.2.0.dist-info/METADATA
ctao_simpipe-0.2.0.dist-info/WHEEL
ctao_simpipe-0.2.0.dist-info/top_level.txt
ctao_simpipe-0.2.0.dist-info/RECORD
