Metadata-Version: 2.4
Name: ctao-simpipe
Version: 0.2.0
Summary: CTAO DPPS Simulation Production Pipeline
Author-email: simpipe developers <simtools-developer@desy.de>
License: BSD 3-Clause License
Project-URL: documentation, https://gitlab.cta-observatory.org/cta-computing/dpps/simpipe/simpipe
Project-URL: repository, https://gitlab.cta-observatory.org/cta-computing/dpps/simpipe/simpipe
Classifier: Intended Audience :: Science/Research
Classifier: License :: OSI Approved :: BSD License
Classifier: Operating System :: OS Independent
Classifier: Programming Language :: Python :: 3 :: Only
Classifier: Programming Language :: Python :: 3.11
Classifier: Programming Language :: Python :: 3.12
Classifier: Programming Language :: Python :: 3.13
Classifier: Topic :: Scientific/Engineering :: Astronomy
Requires-Python: >=3.11
License-File: LICENSE
Requires-Dist: gammasimtools==0.17.0
Provides-Extra: all
Requires-Dist: ctao-simpipe[dev,doc,test]; extra == "all"
Provides-Extra: dev
Requires-Dist: pre-commit; extra == "dev"
Requires-Dist: pylint; extra == "dev"
Requires-Dist: ruff; extra == "dev"
Requires-Dist: towncrier; extra == "dev"
Provides-Extra: doc
Requires-Dist: ctao-sphinx-theme~=0.1.2; extra == "doc"
Requires-Dist: myst-parser; extra == "doc"
Requires-Dist: numpydoc; extra == "doc"
Requires-Dist: sphinx; extra == "doc"
Requires-Dist: sphinx-changelog; extra == "doc"
Requires-Dist: towncrier; extra == "doc"
Provides-Extra: test
Requires-Dist: pytest; extra == "test"
Requires-Dist: pytest-cov; extra == "test"
Requires-Dist: pytest-mock; extra == "test"
Requires-Dist: pytest-requirements; extra == "test"
Requires-Dist: pytest-xdist; extra == "test"
Dynamic: license-file
